pybaked/__init__.py
pybaked/bakedreader.py
pybaked/cli/__init__.py
pybaked/cli/bake.py
pybaked/cli/colors.py
pybaked/cli/read.py
pybaked/cli/unpack.py
pybaked/loader.py
pybaked/protocol.py
pybaked/pybaker.py
pybaked-0.0.17.dist-info/METADATA
pybaked-0.0.17.dist-info/WHEEL
pybaked-0.0.17.dist-info/entry_points.txt
pybaked-0.0.17.dist-info/RECORD
